odoo/addons/base_contextvars/README.rst
odoo/addons/base_contextvars/__init__.py
odoo/addons/base_contextvars/__manifest__.py
odoo/addons/base_contextvars/contextvars_patch.py
odoo/addons/base_contextvars/i18n/base_contextvars.pot
odoo/addons/base_contextvars/readme/DESCRIPTION.rst
odoo/addons/base_contextvars/static/description/icon.png
odoo/addons/base_contextvars/static/description/index.html
odoo/addons/base_contextvars/tests/__init__.py
odoo/addons/base_contextvars/tests/test_contextvars.py
odoo14_addon_base_contextvars-14.0.1.0.4.dist-info/METADATA
odoo14_addon_base_contextvars-14.0.1.0.4.dist-info/WHEEL
odoo14_addon_base_contextvars-14.0.1.0.4.dist-info/top_level.txt
odoo14_addon_base_contextvars-14.0.1.0.4.dist-info/RECORD
